xtor/__init__.py
xtor/cli.py
xtor/tor.py
xtor/utils.py
xtor-0.4.3.dist-info/METADATA
xtor-0.4.3.dist-info/WHEEL
xtor-0.4.3.dist-info/entry_points.txt
xtor-0.4.3.dist-info/RECORD
