Metadata-Version: 2.1
Name: xtor
Version: 0.4.3
Summary: Manage Tor instances
Home-page: https://github.com/khalidelborai/xtor
License: GNU Version 3
Keywords: tor,torrc,torrc manager,tor manager,tor instance,proxy
Author: khalidelborai
Author-email: elboraikhalid@gmail.com
Requires-Python: >=3.7,<4.0
Classifier: License :: Other/Proprietary License
Classifier: Programming Language :: Python :: 3
Classifier: Programming Language :: Python :: 3.7
Classifier: Programming Language :: Python :: 3.8
Classifier: Programming Language :: Python :: 3.9
Classifier: Programming Language :: Python :: 3.10
Classifier: Programming Language :: Python :: 3.11
Requires-Dist: httpx[socks] (>=0.24.1,<0.25.0)
Requires-Dist: stem (>=1.8.2,<2.0.0)
Requires-Dist: typer (>=0.9.0,<0.10.0)
Requires-Dist: where (>=1.0.2,<2.0.0)
Project-URL: Repository, https://github.com/khalidelborai/xtor
